pandas_prototype/__init__.py
pandas_prototype/data_frame.py
pandas_prototype/debug.py
pandas_prototype-1.0.3.dist-info/LICENSE
pandas_prototype-1.0.3.dist-info/METADATA
pandas_prototype-1.0.3.dist-info/WHEEL
pandas_prototype-1.0.3.dist-info/top_level.txt
pandas_prototype-1.0.3.dist-info/RECORD
