Metadata-Version: 2.1
Name: pandas-prototype
Version: 1.0.3
Summary: A package with implementation of famous Pandas library in my way ,  allows you to visualize data using data tables.
Home-page: https://github.com/Sanmeet007/pandas_prototype
Author: Sanmeet Singh
Author-email: ssanmeet123@gmail.com
License: GPL-3.0 license
Keywords: python,pandas,pandas prototype,prototyping,data visualizing,data scientist,data
Platform: UNKNOWN
Classifier: Development Status :: 5 - Production/Stable
Classifier: Intended Audience :: Developers
Classifier: Programming Language :: Python :: 3.10
Classifier: Operating System :: Microsoft :: Windows
License-File: LICENSE
Requires-Dist: json2html
Requires-Dist: prettytable
